{"algebra_exponentials-logarithms.md":"Tr8vOTve","algebra_linear-equations.md":"PNW3nZBP","algebra_product-notation.md":"B_Q58NHE","algebra_quadratics.md":"LpPccxRA","algebra_summation_notation.md":"BoZiUDhB","basics_functions.md":"7Zb2RljB","basics_number-theory.md":"CmeicH8q","basics_order-of-operations.md":"CE1xNgFb","basics_variables-expressions.md":"DB2U1DLM","calculus_limits.md":"dKeolBB9","index.md":"mOTnDMyA","linear-algebra_matrices.md":"BBbJ_BUz","linear-algebra_vectors.md":"DIaXPrFg","statistics_descriptive-stats.md":"CBAuKRkf","statistics_probability.md":"DCW7i-gA","trigonometry_unit-circle.md":"DhbZyPOI"}
